readylog/__init__.py
readylog/decorators.py
readylog/mixins.py
readylog-0.1.1.dist-info/WHEEL
readylog-0.1.1.dist-info/METADATA
readylog-0.1.1.dist-info/RECORD
