Metadata-Version: 2.4
Name: readylog
Version: 0.1.1
Summary: Creates a reasonable logging configuration for a Python project
Keywords: logging,logging configuration
Author: fleetingbytes
Author-email: fleetingbytes <7075397+fleetingbytes@users.noreply.github.com>
License-Expression: BSD-2-Clause
Classifier: Development Status :: 4 - Beta
Classifier: License :: OSI Approved :: BSD License
Classifier: Programming Language :: Python :: 3.11
Classifier: Programming Language :: Python :: 3.12
Classifier: Programming Language :: Python :: 3.13
Classifier: Programming Language :: Python :: 3.14
Classifier: Programming Language :: Python :: 3.15
Requires-Python: >=3.11
Project-URL: Changelog, http://github.com/fleetingbytes/readylog/blob/master/CHANGELOG.md
Project-URL: Documentation, http://github.com/fleetingbytes/readylog/blob/master/README.md
Project-URL: Homepage, http://github.com/fleetingbytes/readylog
Project-URL: Issues, http://github.com/fleetingbytes/readylog/issues
Project-URL: Repository, http://github.com/fleetingbytes/readylog.git
